{
  "settings": {
    "CUSTOM_REGEXPS": {
      "填空题": "",
      "问答题": "((?:[^\\n][\\n]?)+)\\s#flashcard\\s?\\n*((?:\\n(?:^.{1,3}$|^.{4}(?<!<!--).*))+)",
      "问答题（同时生成翻转的卡片<可选>）": "",
      "问答题（同时生成翻转的卡片）": "",
      "问答题（输入答案）": ""
    },
    "FILE_LINK_FIELDS": {
      "填空题": "文字",
      "问答题": "正面",
      "问答题（同时生成翻转的卡片<可选>）": "正面",
      "问答题（同时生成翻转的卡片）": "正面",
      "问答题（输入答案）": "正面"
    },
    "CONTEXT_FIELDS": {},
    "FOLDER_DECKS": {
      "Excalidraw": "",
      "Xmind导图": "",
      "信号与系统": "",
      "政治": "",
      "数学": "",
      "模板": "",
      "笔记照片": "",
      "英语": "",
      "Xmind导图/各类积分之间的联系": "",
      "Xmind导图/定积分-二重积分-三重积分": "",
      "Xmind导图/信号-各类信号之间关系": "",
      "Xmind导图/无穷级数": "",
      "Xmind导图/积分的物理与数学应用": "",
      "信号与系统/真题复盘": "",
      "信号与系统/知识点整理": "",
      "数学/倒计时要背咯": "",
      "数学/知识点整理": "",
      "数学/真题复盘": "",
      "笔记照片/信号图片": "",
      "笔记照片/思维导图": "",
      "笔记照片/政治图片": "",
      "笔记照片/数学图片": "",
      "anki": ""
    },
    "FOLDER_TAGS": {
      "Excalidraw": "",
      "Xmind导图": "",
      "信号与系统": "",
      "政治": "",
      "数学": "",
      "模板": "",
      "笔记照片": "",
      "英语": "",
      "Xmind导图/各类积分之间的联系": "",
      "Xmind导图/定积分-二重积分-三重积分": "",
      "Xmind导图/信号-各类信号之间关系": "",
      "Xmind导图/无穷级数": "",
      "Xmind导图/积分的物理与数学应用": "",
      "信号与系统/真题复盘": "",
      "信号与系统/知识点整理": "",
      "数学/倒计时要背咯": "",
      "数学/知识点整理": "",
      "数学/真题复盘": "",
      "笔记照片/信号图片": "",
      "笔记照片/思维导图": "",
      "笔记照片/政治图片": "",
      "笔记照片/数学图片": "",
      "anki": ""
    },
    "Syntax": {
      "Begin Note": "START",
      "End Note": "END",
      "Begin Inline Note": "STARTI",
      "End Inline Note": "ENDI",
      "Target Deck Line": "TARGET DECK",
      "File Tags Line": "FILE TAGS",
      "Delete Note Line": "DELETE",
      "Frozen Fields Line": "FROZEN"
    },
    "Defaults": {
      "Tag": "Obsidian_to_Anki",
      "Deck": "Default",
      "Scheduling Interval": 0,
      "Add File Link": false,
      "Add Context": false,
      "CurlyCloze": false,
      "CurlyCloze - Highlights to Clozes": false,
      "ID Comments": true,
      "Add Obsidian Tags": false
    }
  },
  "Added Media": [
    "image-20221027105130044.png",
    "Pasted image 20221105154319.png",
    "Pasted image 20221116124850.png",
    "Pasted image 20221116124249.png",
    "Pasted image 20221116124658.png",
    "Pasted image 20221104172505.png",
    "Pasted image 20221103175506.png",
    "Pasted image 20221105154336.png",
    "Pasted image 20221123144447.png",
    "Pasted image 20221123144504.png",
    "Pasted image 20221123145606.png",
    "Pasted image 20221123145647.png",
    "Pasted image 20221123150140.png",
    "Pasted image 20221123150215.png",
    "Pasted image 20221123152331.png",
    "Pasted image 20221123152436.png",
    "Pasted image 20221123154914.png",
    "Pasted image 20221123155141.png",
    "Pasted image 20221126165148.png",
    "Pasted image 20221128155250.png",
    "Pasted image 20221128155424.png",
    "Pasted image 20221128155447.png",
    "Pasted image 20221128155541.png",
    "Pasted image 20221128155612.png",
    "Pasted image 20221128173359.png",
    "Pasted image 20221130160125.png",
    "Pasted image 20221130160203.png",
    "Pasted image 20221206170346.png",
    "Pasted image 20221206170447.png",
    "Pasted image 20221209195445.png",
    "Pasted image 20221209195518.png",
    "Pasted image 20221211165706.png",
    "Pasted image 20221211165729.png",
    "Pasted image 20221214172118.png",
    "Pasted image 20221214172214.png",
    "Pasted image 20221219184455.png",
    "Pasted image 20221219184533.png",
    "Pasted image 20221219184559.png",
    "Pasted image 20221219184632.png"
  ],
  "File Hashes": {
    "政治anki.md": "b87909f67e710681085c7c47edcd0b02",
    "英语/英语真题奇淫巧计.md": "87bfd7481f18d32ba7e0325feb8a220c",
    "英语/阅读单词.md": "e8cd51415e9ca68ab1389a5687866809",
    "英语/英语阅读总结.md": "cd1cbed01608f71df90196eb3654dd42",
    "英语/英语作文.md": "caa8f52c1e99caefb76f224cc7a9f740",
    "英语/单词.md": "059aced9db6634e1f0bfaa16edf784dd",
    "英语/红宝书单词.md": "7ecc41e957c10026ebdd7e42d2d27720",
    "英语/英语新题型.md": "38ea775bf0693d98ef8522520730f967",
    "英语/文章看不懂怎么写阅读.md": "eeb0805705d29eca386322ce3797e44c",
    "英语/必会写单词.md": "758b2d27cdb83ba481c2897e3c470df9",
    "考研各科分数.md": "c59e9a94e77583dd9c1c89001a9cc360",
    "模板/试卷复盘.md": "0ec8fb88a0f9df543a9fdc3717dec147",
    "模板/数学试卷复盘模板.md": "b3025cff86b026eac9503f033871e92d",
    "框图画法.md": "78cb8b56e42c0a7f6d3746c46fb840d8",
    "数学/记录一些题目.md": "995feeb362e9e443f046f346ec54d3c2",
    "数学/真题复盘/2022年考研数学真题复盘.md": "bd6a436b77ce0b31731eb7676a4965b8",
    "数学/真题复盘/2021年考研数学真题复盘.md": "d28d7eeeb2160ca50e265d29b9757d5d",
    "数学/真题复盘/2019年考研数学真题复盘.md": "fc7cb40440e7ea548f6af1d60c4ef77c",
    "数学/知识点整理/高数错题笔记.md": "d56ff36c591793f45cc1d5f60b7e4e9d",
    "数学/知识点整理/3-8统计量.md": "1d7da603335f8f5b87506eb062d8d9e2",
    "数学/知识点整理/常见空间曲面图像与极坐标图像.md": "b13b36e93bdec0872b97e47dec2c9957",
    "数学/知识点整理/3-9参数估计与假设检验.md": "7381aa80b930a56c4e134fdc55b0e5cd",
    "数学/知识点整理/3-7大数定律与中心极限定理.md": "f9ad978db7c7d31bb7d12241b1c31150",
    "数学/知识点整理/3-5多维随机变量函数的分布.md": "f7da4c616fab896771697a267ad1a564",
    "数学/知识点整理/3-6数字特征.md": "b2ed68bf45eb70d004ee049e983b4ced",
    "数学/知识点整理/3-3一维随机变量函数的分布.md": "5f4f671179dfe7edfe11f7f7253c8933",
    "数学/知识点整理/3-4多维随机变量及其分布.md": "f83c37334d9f7c47878c4f6315620244",
    "数学/知识点整理/3-2一维随机变量及其分布.md": "1b849dc7c46e2ba8a5b9648e9860f71d",
    "数学/知识点整理/3-1随机事件和概率.md": "c796d861119052067134ef3ec9683920",
    "数学/知识点整理/2-4方程组.md": "b86880b7dce9bf91fd3bc379b12a0da0",
    "数学/知识点整理/2-6二次型.md": "9cd6031cd7c8b83204c842e16c90ecad",
    "数学/知识点整理/2-5特征值.md": "7181a2599a2e5dfbcbc509f43de23b34",
    "数学/知识点整理/2-1行列式.md": "2af265abe7318299c6f89224fa50fb78",
    "数学/知识点整理/2-3向量.md": "0ab330fd9fdc2929a15761d609f04d14",
    "数学/知识点整理/2-2矩阵.md": "d0afed0852cee9b0afadf603839d8496",
    "数学/知识点整理/1-9一元积分计算的几种方法.md": "afe47a66c8e8d3acc680bb12747afff5",
    "数学/知识点整理/1-7一元函数微分学的应用.md": "92ca9a4c900fff1050c0aaa8fb892949",
    "数学/知识点整理/1-8一元函数积分学的基本概念.md": "5b58a7c8515fc47aa2892ffd6278503c",
    "数学/知识点整理/1-6一元函数微分学的证明.md": "3829792dba6772c4663a3a97e8b1ac22",
    "数学/知识点整理/1-5一元微分的几何应用.md": "e82c9282bfb45fc5c35c2408e66648d2",
    "数学/知识点整理/1-4一元微分学的计算.md": "ba794dbe11c48c5b3dce24cc4f576235",
    "数学/知识点整理/1-3一元函数微分学.md": "278290811efd6461f80bcaac16f9d099",
    "数学/知识点整理/1-2数列极限.md": "9aa0f6e7b5001b6dfceb585a381d6efc",
    "数学/知识点整理/1-1函数极限.md": "c5254ad75743b382853a2343dfd98dd9",
    "数学/知识点整理/1-18多元函数积分学.md": "a6b4dec7bd28f3cb2c5ffbde2cfcc314",
    "数学/知识点整理/1-16无穷级数.md": "9e79738de716a4d3c50da573f5c9e1e0",
    "数学/知识点整理/1-17多元函数积分学的预备知识.md": "455788d59b006f3e560051e4443cf4bf",
    "数学/知识点整理/1-15微分方程.md": "ee51fe11494c66cf4280b6448d48620c",
    "数学/知识点整理/1-14二重积分.md": "7fc00c9fe70a31184a0739c191a412c4",
    "数学/知识点整理/1-12一元积分的物理应用.md": "b8f81833b4992e91b10fa66b205f43c5",
    "数学/知识点整理/1-13多元函数微分学.md": "b83adf17532dbce345a62140c10da6c0",
    "数学/知识点整理/1-11一元积分证明题.md": "81541edb4ca1fac9587dcfaadf36d9ca",
    "数学/知识点整理/1-0-源-极限.md": "23e415ab6296835d1ec33cb97accc7d0",
    "数学/倒计时要背咯/记录真题考点.md": "2e3068b7cf4ebcfe01bf5259a61c6b6e",
    "数学/倒计时要背咯/记录一些题目中的特例.md": "7526cdc7459f1846bece444b952b7252",
    "数学/倒计时要背咯/我老是搞错的点.md": "03579aad82f378d78574f59dc9f73081",
    "数学/倒计时要背咯/数学思想.md": "6ab6451dd171e49d6b7dfdf1261eac24",
    "数学/倒计时要背咯/规范解题步骤.md": "d5f063d79426d42c2b65be5c84901dba",
    "数学/倒计时要背咯/我就说这样好用吧.md": "e60585e7249398087a2234fb443f824a",
    "数学/倒计时要背咯/整理要背下来的东西.md": "c091b8644293bdf0d505d8a5eff62abb",
    "数学/记录一些积分.md": "a6790f260b90ea5dba7dfd4d433201c5",
    "政治/腿姐技巧班.md": "62f84795e937c84b5c791d09bac02a05",
    "政治/毛中特.md": "70e35e94d593a0c33bbcc89efd5aa68c",
    "政治/整理要背下来的东西.md": "8ee882101415be2edf2736e4f93e4a04",
    "政治/政治错题笔记.md": "eff5814973f8ce24bd2aeae9b98260fd",
    "政治/史纲概要.md": "c4c541b6f7f566143959d65ec771aa75",
    "政治/中特错题笔记.md": "9c2ad05c82f810ce706d23dcd71866da",
    "信号与系统/证明汇总.md": "c695d1a95caafb390a102b3e6c17a33d",
    "信号与系统/规范信号做题步骤.md": "c85a3ebdf03bd26909cd90e7c3d0fa92",
    "信号与系统/知识点整理/2.时域分析法.md": "0830767d6899948555bc9bbb8543b2b5",
    "信号与系统/知识点整理/6.Z变换.md": "e0119eb2375f4e7ea11fae0fd135d649",
    "信号与系统/知识点整理/5.拉斯变换.md": "663e4d504eca55e080211fe89830c74b",
    "信号与系统/知识点整理/4.信号的频域分析.md": "e8c09f26ce17ea978a1b8f8f3ea83880",
    "信号与系统/知识点整理/3.傅里叶变换.md": "4cfe4297cafa0a98b3fc7d081643a5aa",
    "信号与系统/知识点整理/1.信号与系统基本概念.md": "add065b8ca042ad795a0ec5082149e18",
    "信号与系统/知识点整理/0.电子科技大学858考试大纲.md": "200572ac1722940ec3902e4bb480aa34",
    "信号与系统/电路题综合.md": "bc88306bfaa4750222739271cc27495e",
    "信号与系统/真题复盘/2022年电科真题复盘.md": "803e5de206596363e92de657b4e745da",
    "信号与系统/真题复盘/2020年电科真题复盘.md": "87b39f232d4ab330a4f691fe6af4c9ab",
    "信号与系统/真题复盘/2021年电科真题复盘.md": "e2bc521413fd6dc5da4d635ac9149f12",
    "信号与系统/真题复盘/2019年电科真题复盘.md": "526d202c19bc56befb83a84979e1eeaa",
    "信号与系统/真题复盘/2018年电科真题复盘.md": "9a79920fc8599c9a320779fdc1a5f5b0",
    "信号与系统/真题复盘/2017年电科真题复盘.md": "2d99b3bcbc4a22255adc355e2eb9c0d8",
    "信号与系统/真题复盘/2016年电科真题复盘.md": "d41d8cd98f00b204e9800998ecf8427e",
    "信号与系统/真题复盘/2015年电科真题复盘.md": "c263ba67bda9ec893a4c8d2d1384d5cb",
    "信号与系统/真题复盘/2014年电科真题复盘.md": "c3ef4abeed096fee04a7a84b525ea284",
    "信号与系统/整理要背下来的东西.md": "92b42dbdd56a0ddc10a02001eca26b83",
    "信号与系统/必背是必备.md": "e2e5f58f604743da09b335109c7b1307",
    "信号与系统/奥本海姆.md": "b7df28ae2ff83e17d672116fdc478fa4",
    "信号与系统/信号与系统错题集.md": "b75ee381925ac97d2c1b427365fc8c1b",
    "信号与系统/信号与系统的题型.md": "fcc4c77378856d94e624bbe27d737e9d",
    "信号与系统/一些信号的频谱图解.md": "1f312bfb4f51e37cdb9100815036a5a1",
    "不要管我叫啥名.md": "c6bcd24722cb8ddbb5c7009090f3f84c",
    "Xmind导图/信号-各类信号之间关系/FT-ST.md": "cacfe9a4187bb4e7a4967fcbd944a250",
    "Xmind导图/信号-各类信号之间关系/由z变换求DFT和DFS.md": "eff21ed68ec5b06f3023128a07d79a2e",
    "Xmind导图/信号-各类信号之间关系/FS-FT.md": "65f160489901b5bac2fd5a71a1011564",
    "Xmind导图/各类积分之间的联系/高斯公式.md": "097d51d06a5c4e3a69ec62f416a6867f",
    "Xmind导图/各类积分之间的联系/格林公式.md": "c19c8dd0d8706efffd613eda9b7804ac",
    "Xmind导图/各类积分之间的联系/第二型曲面积分换元为二重积分.md": "e753ceef51b6ee92547bd59fd55d810a",
    "Xmind导图/各类积分之间的联系/第一型曲面积分.md": "76ac7a5ad5241a20a1854e0e3dba591c",
    "Xmind导图/各类积分之间的联系/定积分.md": "3ca460943dc812488cd830c7f0fb92c0",
    "Xmind导图/各类积分之间的联系/斯托克斯公式.md": "d044e5534f7b6f9fa4ff192af2d47c45",
    "Xmind导图/各类积分之间的联系/二重积分.md": "629f8a9dd91ceccb674a7361c64a205b",
    "Xmind导图/各类积分之间的联系/三重积分.md": "c1c7eea0d9d2bb45af4bae8ffc4bd219",
    "Excalidraw/频谱方波-正弦加持.excalidraw.md": "c4a55fa32c7d02f39f26a06c4061d175",
    "Excalidraw/频谱方波.excalidraw.md": "c176d1f54fcc8a369a3c02b69f3e62e6",
    "Excalidraw/频谱三角与类三角.excalidraw.md": "fa0d8c80820b952c29dc38883df4a92f",
    "Excalidraw/采样原始信号.excalidraw.md": "8ac34145054c3d6225443c19d07cb31c",
    "Excalidraw/随机事件概率分布.excalidraw.md": "1f2b5391e75bb1d891b9069f66d6b039",
    "Excalidraw/采样之后信号.md": "47a22d1ecb8f63027f32141c29d1eb97",
    "Excalidraw/线性代数之间联系.excalidraw.md": "f5587cf35f37a21e768d5828743c4244",
    "Excalidraw/矩阵可相似对角化 2022-09-08 11.39.12.excalidraw.md": "2f20fc07ac09e7beb2998ca469d67476",
    "Excalidraw/等价-相似-合同.excalidraw.md": "5535d9fcb74734badaaa3ff9aacf648e",
    "Excalidraw/两个矩阵相似.excalidraw.md": "d3b151606d48264b7942044c88a9744c",
    "Excalidraw/Drawing 2022-10-07 09.11.36.excalidraw.md": "f1c9f42e2b2c82b3557784e9ac8c98cc",
    "Excalidraw/时域类三角.excalidraw.md": "ca505717cb88e7d84d1593fdf1a7ac5f",
    "Excalidraw/Drawing 2022-09-23 21.10.29.excalidraw.md": "acf6eea9ffb83bb930522b358ef473dd",
    "Excalidraw/0-源-极限 2022-08-14 23.01.46.excalidraw.md": "a5c85fae8c53690dfb3202af1805d48c",
    "README.md": "2eb44a56cd8b0e9e83ca61021840e256",
    "markdown.md": "77053d4e0cf75acd5cb90500b4260dde",
    "信号与系统anki.md": "ee58f2ff0b1d214cf52c9bcceb9339de",
    "数学anki.md": "dc1a97608ef033eb2b8388f3aaff51ee",
    "anki/政治anki.md": "b5b94a71f4040cee882154692b805880",
    "anki/信号与系统anki.md": "3a1626707a49994682da0595c92320c4",
    "anki/数学anki.md": "10510ddf944f910d4d4d99d927863b5a",
    "数学/常见空间曲面图像与极坐标图像.md": "d42b8c4c6b839cd9ac303a789956d15a",
    "anki/英语anki.md": "0f7ec19fd91cf702e72185a22381c909",
    "最后十天-关于我为什么数学模考波动巨大的反思与总结.md": "63625cdf94506391b1a16b189269929d"
  },
  "fields_dict": {
    "填空题": [
      "文字",
      "背面额外"
    ],
    "问答题": [
      "正面",
      "背面"
    ],
    "问答题（同时生成翻转的卡片<可选>）": [
      "正面",
      "背面",
      "添加翻转的卡片"
    ],
    "问答题（同时生成翻转的卡片）": [
      "正面",
      "背面"
    ],
    "问答题（输入答案）": [
      "正面",
      "背面"
    ]
  }
}